locust_plugins/__init__.py
locust_plugins/_version.py
locust_plugins/connection_pools.py
locust_plugins/csvreader.py
locust_plugins/mongoreader.py
locust_plugins/py.typed
locust_plugins/transaction_manager.py
locust_plugins/utils.py
locust_plugins/wait_time.py
locust_plugins/dashboards/locust-grafana/Dockerfile
locust_plugins/dashboards/locust-grafana/Makefile
locust_plugins/dashboards/locust-grafana/create_datasource.sh
locust_plugins/dashboards/locust-grafana/grafana_setup.sh
locust_plugins/dashboards/locust-grafana/import_dashboards.sh
locust_plugins/dashboards/locust-timescale/Dockerfile
locust_plugins/dashboards/locust-timescale/Makefile
locust_plugins/dashboards/locust-timescale/timescale_schema.sql
locust_plugins/dashboards/locust-timescale/zz_hypertable.sql
locust_plugins/listeners/__init__.py
locust_plugins/listeners/appinsights.py
locust_plugins/listeners/cloudwatch.py
locust_plugins/listeners/jmeter.py
locust_plugins/listeners/timescale.py
locust_plugins/users/__init__.py
locust_plugins/users/kafka.py
locust_plugins/users/mqtt.py
locust_plugins/users/playwright.py
locust_plugins/users/resource.py
locust_plugins/users/rest.py
locust_plugins/users/socketio.py
locust_plugins/users/webdriver.py
Altair_mcb_locust_plugins-0.0.4.dist-info/LICENSE
Altair_mcb_locust_plugins-0.0.4.dist-info/METADATA
Altair_mcb_locust_plugins-0.0.4.dist-info/WHEEL
Altair_mcb_locust_plugins-0.0.4.dist-info/top_level.txt
Altair_mcb_locust_plugins-0.0.4.dist-info/RECORD
