Metadata-Version: 2.1
Name: Altair-mcb-locust-plugins
Version: 0.0.4
Summary: A sample test package
Home-page: https://github.com/mcraj4u/altair-coe-locust-plugins
Author: Bhagyaraj
Author-email: mc_raj4u@yahoo.co.in
License: MIT
Platform: UNKNOWN
Requires-Python: >=3.8
License-File: LICENSE
Requires-Dist: locust (>=2.20.0)
Requires-Dist: typing-extensions
